Metadata-Version: 2.1
Name: fileparse-tobiasli
Version: 1.0.7
Summary: Tools for parsing text content and creating data models for the content found.
Home-page: https://github.com/tobiasli/fileparse
Author: Tobias Litherland
Author-email: tobiaslland@gmail.com
License: UNKNOWN
Platform: UNKNOWN
Classifier: Programming Language :: Python :: 3
Classifier: License :: OSI Approved :: MIT License
Classifier: Operating System :: OS Independent
